nonparstat/Cucconi.py
nonparstat/Lepage.py
nonparstat/PodgorGastwirth.py
nonparstat/__init__.py
nonparstat/__version__.py
NonParStat-0.0.3.dist-info/LICENSE
NonParStat-0.0.3.dist-info/METADATA
NonParStat-0.0.3.dist-info/WHEEL
NonParStat-0.0.3.dist-info/top_level.txt
NonParStat-0.0.3.dist-info/RECORD
