Metadata-Version: 2.1
Name: NonParStat
Version: 0.0.3
Summary: A collection of various non-parametric tests.
Home-page: https://grzegorzmika.github.io/NonParStat/
Author: Grzegorz Mika
Author-email: g.w.mika@gmail.com
License: MIT
Platform: UNKNOWN
Classifier: License :: OSI Approved :: MIT License
Classifier: Programming Language :: Python
Classifier: Programming Language :: Python :: 3
Classifier: Programming Language :: Python :: 3.6
Classifier: Programming Language :: Python :: 3.7
Classifier: Programming Language :: Python :: 3.8
Classifier: Programming Language :: Python :: Implementation :: CPython
Classifier: Programming Language :: Python :: Implementation :: PyPy
Requires-Python: >=3.6
Requires-Dist: numpy
Requires-Dist: scipy
